pyTooling/TerminalUI/__init__.py
pyTooling/TerminalUI/py.typed
pyTooling.TerminalUI-1.5.9.dist-info/LICENSE.md
pyTooling.TerminalUI-1.5.9.dist-info/METADATA
pyTooling.TerminalUI-1.5.9.dist-info/WHEEL
pyTooling.TerminalUI-1.5.9.dist-info/top_level.txt
pyTooling.TerminalUI-1.5.9.dist-info/RECORD
