Metadata-Version: 2.1
Name: pyTooling.TerminalUI
Version: 1.5.9
Summary: A set of helpers to implement a text user interface (TUI) in a terminal.
Home-page: https://GitHub.com/pyTooling/pyTooling.TerminalUI
Author: Patrick Lehmann
Author-email: Paebbels@gmail.com
License: Apache-2.0
Project-URL: Documentation, https://pyTooling.GitHub.io/pyTooling.TerminalUI
Project-URL: Source Code, https://GitHub.com/pyTooling/pyTooling.TerminalUI
Project-URL: Issue Tracker, https://GitHub.com/pyTooling/pyTooling.TerminalUI/issues
Keywords: terminal,shell,text user interface,TUI,console,message logging
Classifier: Operating System :: OS Independent
Classifier: Intended Audience :: Developers
Classifier: Topic :: Utilities
Classifier: License :: OSI Approved :: Apache Software License
Classifier: Programming Language :: Python :: 3 :: Only
Classifier: Programming Language :: Python :: 3.7
Classifier: Programming Language :: Python :: 3.8
Classifier: Programming Language :: Python :: 3.9
Classifier: Programming Language :: Python :: 3.10
Classifier: Development Status :: 5 - Production/Stable
Requires-Python: >=3.7
License-File: LICENSE.md
Requires-Dist: colorama (>=0.4.5)
Requires-Dist: pyTooling (>=2.1.0)
Provides-Extra: all
Requires-Dist: sphinxcontrib-mermaid (>=0.7.1) ; extra == 'all'
Requires-Dist: sphinx-autodoc-typehints (>=1.18.1) ; extra == 'all'
Requires-Dist: autoapi ; extra == 'all'
Requires-Dist: sphinx (>=5.0.2) ; extra == 'all'
Requires-Dist: colorama (>=0.4.5) ; extra == 'all'
Requires-Dist: sphinx-fontawesome (>=0.0.6) ; extra == 'all'
Requires-Dist: pyTooling (>=2.1.0) ; extra == 'all'
Provides-Extra: doc
Requires-Dist: sphinxcontrib-mermaid (>=0.7.1) ; extra == 'doc'
Requires-Dist: sphinx-autodoc-typehints (>=1.18.1) ; extra == 'doc'
Requires-Dist: autoapi ; extra == 'doc'
Requires-Dist: sphinx (>=5.0.2) ; extra == 'doc'
Requires-Dist: colorama (>=0.4.5) ; extra == 'doc'
Requires-Dist: sphinx-fontawesome (>=0.0.6) ; extra == 'doc'
Requires-Dist: pyTooling (>=2.1.0) ; extra == 'doc'
